{
  "cricket": [
    {
      "c": "Dates",
      "i": "21 Jan 2026",
      "l": "Date"
    },
    {
      "c": "",
      "i": "dfasdfasdf",
      "l": "dsfdsafsdafasdfasdfasdfasdfasdfasdfasdfasdfasdfasdfasdfasdfasdfasdfasdfsdf"
    }
  ],
  "mantis": [
    {
      "c": "Dates",
      "i": "Jan 21, 2026",
      "l": "Date"
    },
    {
      "c": "Dates",
      "i": "** TEST ** \n- tesat\n-dfsasdf",
      "l": "test"
    },
    {
      "c": "Formats",
      "i": "dfsl;kajsdlfjalsdjfl;kasjdflk;ajsdfkl;jaslk;dfjlk;asjdfl;ajsdflk;ajsldf;jlas;dfjl;asjdfl;sjadf\n**lkjflsdhflkahsdfasdf**\n- klsdjflkajsdfljasdf\n- klajsdfl;jkasdfsadf",
      "l": "dsfaksdkfkasgagsfgasdgfgasgdakgsfgasgfgasdkgfgasdgfgasgdfgasdfasdfasdf"
    }
  ]
}