{
  "cricket": [
    {
      "c": "Dates",
      "f": false,
      "i": "**Standard Format: Default to “DD Month YYYY” for all dates**\nEx.:\n-**\"January fifteenth\" → 15 January 2025**\n-**\"March three\" → 3 March 2025**\n-**\"January fifteenth twenty twenty-four\" → 15 January 2024**\n**Year Expansion: Always expand to four digits**\n-**\"twenty-five\" (referring to year) → 2025**\n-**\"twenty-four\" (referring to year) → 2024**\n**Date with Ordinal vs. Cardinal: Default to cardinal**\n-**\"twenty-first\" → 21**\n**Month Names: Spell out in full**\n-**Jan → January**\n**Numerical-only dates:**\n-**\"twelve ten twenty five\" → 10 December 2025**\n-**\"three fifteen twenty four\" → 15 March 2024**\n\n**Well-known Date Exceptions:**\n-**\"nine eleven\" → 9/11 (referring to September 11, 2001)**",
      "id": "b07404e3-68a8-4481-a7f8-cc490e9a69da",
      "l": "Date"
    },
    {
      "c": "",
      "f": false,
      "i": "**Standard Format**\n***Transcribe time as h:mmAM/PM; no periods and no space***\n✅ “9 in the evening” → 9:00PM**\n**Time in a Series**\n**Repeat the unit with each number.**\n✅ “People have about a 20-minute, 25-minute, maybe a 30-minute drive”**\n**Time Ranges**\n**Use hyphen with no spaces.**\n✅ “They went to work from 9:00AM-5:00PM”\n**Follow standard time format when converting:**\n✅ “7:00AM to midnight” → 7:00AM–12:00AM\n✅ “7:00AM to 12 noon” → 7:00AM–12:00PM\n**Non-Clock Durations**\n**For minutes, hours, or months not tied to a clock:**\n✅ “eight to 10 minutes” (following number rule: spell out 1–9, use numerals for 10+)\n✅ “24 to 36-month average”\n✅ “22 to 36-hour process”",
      "id": "3e4e22f9-d19d-4322-aab2-15178b8398b0",
      "l": "TIME"
    }
  ],
  "mantis": [
    {
      "c": "Dates",
      "f": false,
      "i": "Format : Month Date, Year \n*****Month Names: Spell out month names in full.*****\n**January, February, March, April, May, June, July, August, September, October, November, December**\n***Ex.:*** \n-**January 21, 2026**\n-**\"January fifteenth\" → January 15th**\n-**March three\" → March 3**\n-*****\"January fifteenth twenty twenty-four\"*** → January 15th, 2024**\n-*****\"December twenty-first twenty-five\"*** → December 21st, 2025**\n**Year Expansion: Always expand abbreviated years to four digits when mentioned.**\n-*****\"twenty-five\" (when referring to a year)*** → 2025**\n-*****\"twenty-four\" (when referring to a year)*** → 2024**\n**Date with Ordinal/Cardinal Indicators: Use proper ordinals only if that's how dictated. If the speaker uses cardinal numbers, retain them as cardinal.**\n-*****If dictated as \"first, second, third\"*** → 1st, 2nd, 3rd, etc.**\n-*****If dictated as \"one, two, three\"*** → 1, 2, 3, etc.**\n***Ex.:***\n-**\"twenty-first\" → 21st, but \"twenty-one\" → 21**\n-**Jan → January**\n**Numerical-only dates: When speakers use numerical format:**\n-**\"twelve ten twenty five\" → 12/10/2025**\n-**\"three fifteen twenty four\" → 03/15/2024**\n-**“six one twenty twenty five” → 06/01/2025**\n**Well-known Date Exceptions: Retain commonly recognized numerical formats for culturally significant dates.**\n-**\"nine eleven\" → 9/11 (referring to the September 11, 2001 terrorist attacks)**",
      "id": "d0cc0eb9-0f2f-4bcd-9033-636f3c6909be",
      "l": "Date"
    }
  ]
}